swagger_client/__init__.py
swagger_client/api_client.py
swagger_client/configuration.py
swagger_client/rest.py
swagger_client/api/__init__.py
swagger_client/api/artifact_api.py
swagger_client/api/auditlog_api.py
swagger_client/api/gc_api.py
swagger_client/api/icon_api.py
swagger_client/api/ping_api.py
swagger_client/api/preheat_api.py
swagger_client/api/project_api.py
swagger_client/api/replication_api.py
swagger_client/api/repository_api.py
swagger_client/api/robot_api.py
swagger_client/api/robotv1_api.py
swagger_client/api/scan_api.py
swagger_client/api/systeminfo_api.py
swagger_client/models/__init__.py
swagger_client/models/access.py
swagger_client/models/addition_link.py
swagger_client/models/addition_links.py
swagger_client/models/annotations.py
swagger_client/models/artifact.py
swagger_client/models/audit_log.py
swagger_client/models/authproxy_setting.py
swagger_client/models/cve_allowlist.py
swagger_client/models/cve_allowlist_item.py
swagger_client/models/error.py
swagger_client/models/errors.py
swagger_client/models/execution.py
swagger_client/models/extra_attrs.py
swagger_client/models/gc_history.py
swagger_client/models/general_info.py
swagger_client/models/icon.py
swagger_client/models/instance.py
swagger_client/models/label.py
swagger_client/models/metadata.py
swagger_client/models/metrics.py
swagger_client/models/native_report_summary.py
swagger_client/models/permission.py
swagger_client/models/platform.py
swagger_client/models/preheat_policy.py
swagger_client/models/project.py
swagger_client/models/project_deletable.py
swagger_client/models/project_metadata.py
swagger_client/models/project_req.py
swagger_client/models/project_summary.py
swagger_client/models/project_summary_quota.py
swagger_client/models/provider_under_project.py
swagger_client/models/reference.py
swagger_client/models/registry.py
swagger_client/models/registry_credential.py
swagger_client/models/replication_execution.py
swagger_client/models/replication_task.py
python_harbor_client-1.0.0.dist-info/METADATA
python_harbor_client-1.0.0.dist-info/WHEEL
python_harbor_client-1.0.0.dist-info/top_level.txt
python_harbor_client-1.0.0.dist-info/RECORD
